genericrawl/__init__.py
genericrawl/__main__.py
genericrawl/color_schemes.py
genericrawl/entity.py
genericrawl/entity_templates.py
genericrawl/fov.py
genericrawl/game_messages.py
genericrawl/game_states.py
genericrawl/input.py
genericrawl/main.py
genericrawl/menu.py
genericrawl/render.py
genericrawl/status_effect.py
genericrawl/components/__init__.py
genericrawl/components/ai.py
genericrawl/components/container.py
genericrawl/components/equipment.py
genericrawl/components/fighter.py
genericrawl/components/item.py
genericrawl/components/sight.py
genericrawl/components/slots.py
genericrawl/data/__init__.py
genericrawl/data/arial10x10.png
genericrawl/map/__init__.py
genericrawl/map/dungeon_generator.py
genericrawl/map/game_map.py
genericrawl/map/tile.py
genericrawl-1.2.1.dist-info/entry_points.txt
genericrawl-1.2.1.dist-info/LICENSE.txt
genericrawl-1.2.1.dist-info/WHEEL
genericrawl-1.2.1.dist-info/METADATA
genericrawl-1.2.1.dist-info/RECORD
