Metadata-Version: 2.1
Name: genericrawl
Version: 1.2.1
Summary: A generic roguelike following the Python 3/libtcod tutorial.
Author: Aaron Friesen
Classifier: License :: OSI Approved :: MIT License
Requires-Dist: tcod ~= 13.6.1
Project-URL: Home, https://frie.dev/genericrawl
